kraken_db/__init__.py
kraken_db/flask_routes.py
kraken_db/kraken_data_proc.py
kraken_db/kraken_db.py
kraken_db_sqlite-0.0.29.dist-info/LICENSE.txt
kraken_db_sqlite-0.0.29.dist-info/METADATA
kraken_db_sqlite-0.0.29.dist-info/WHEEL
kraken_db_sqlite-0.0.29.dist-info/top_level.txt
kraken_db_sqlite-0.0.29.dist-info/RECORD
