Metadata-Version: 2.1
Name: kraken-db-sqlite
Version: 0.0.29
Summary: Kraken DB SQLITE
Home-page: https://github.com/tactik8/kraken_db_sqlite
Author: Tactik8
Author-email: info@tactik8.com
License: MIT
Platform: UNKNOWN
Classifier: License :: OSI Approved :: MIT License
Classifier: Programming Language :: Python :: 3
Classifier: Programming Language :: Python :: 3.8
License-File: LICENSE.txt
Requires-Dist: SQLAlchemy
Requires-Dist: Flask
